geojp/__init__.py
geojp/basemaps.py
geojp/common.py
geojp/foliumap.py
geojp/geojp.py
geojp/legends.py
geojp/map_widgets.py
geojp/osm.py
geojp/pc.py
geojp/plot.py
geojp/stac.py
geojp/toolbar.py
geojp/utils.py
geojp-0.0.6.dist-info/LICENSE
geojp-0.0.6.dist-info/METADATA
geojp-0.0.6.dist-info/WHEEL
geojp-0.0.6.dist-info/entry_points.txt
geojp-0.0.6.dist-info/top_level.txt
geojp-0.0.6.dist-info/RECORD
