Metadata-Version: 2.1
Name: geojp
Version: 0.0.6
Summary: A python package for my Geospacial Analysis class
Author-email: Brycen Harris <bharri94@vols.utk.edu>
License: MIT License
Project-URL: Homepage, https://github.com/BrycenHarris/geojp
Keywords: geojp
Classifier: Intended Audience :: Developers
Classifier: License :: OSI Approved :: MIT License
Classifier: Natural Language :: English
Classifier: Programming Language :: Python :: 3.8
Classifier: Programming Language :: Python :: 3.9
Classifier: Programming Language :: Python :: 3.10
Classifier: Programming Language :: Python :: 3.11
Classifier: Programming Language :: Python :: 3.12
Requires-Python: >=3.8
License-File: LICENSE
Requires-Dist: numpy
Requires-Dist: ipyleaflet
Requires-Dist: leafmap
Provides-Extra: all
Requires-Dist: geojp[extra] ; extra == 'all'
Provides-Extra: extra
Requires-Dist: pandas ; extra == 'extra'
